<?xml version="1.0"?>
<!DOCTYPE hibernate-mapping PUBLIC "-//Hibernate/Hibernate Mapping DTD 3.0//EN"
"http://www.hibernate.org/dtd/hibernate-mapping-3.0.dtd">
<!-- Generated Oct 13, 2018 5:50:51 PM by Hibernate Tools 4.3.1 -->
<hibernate-mapping>
    <class name="entity.Category" table="category" catalog="shop_online" optimistic-lock="version">
        <id name="catId" type="java.lang.Integer">
            <column name="cat_id" />
            <generator class="identity" />
        </id>
        <property name="catName" type="string">
            <column name="cat_name" length="45" not-null="true" />
        </property>
        <property name="catDesc" type="string">
            <column name="cat_desc" length="200" not-null="true" />
        </property>
        <set name="subCategories" table="sub_category" inverse="true" lazy="true" fetch="select">
            <key>
                <column name="cat_id" not-null="true" />
            </key>
            <one-to-many class="entity.SubCategory" />
        </set>
    </class>
</hibernate-mapping>
